nucypher_core/__init__.py
nucypher_core/__init__.pyi
nucypher_core/_nucypher_core.cp311-win_amd64.pyd
nucypher_core/ferveo.py
nucypher_core/ferveo.pyi
nucypher_core/py.typed
nucypher_core/umbral.py
nucypher_core/umbral.pyi
nucypher_core-0.15.0.dist-info/licenses/LICENSE
nucypher_core-0.15.0.dist-info/METADATA
nucypher_core-0.15.0.dist-info/WHEEL
nucypher_core-0.15.0.dist-info/top_level.txt
nucypher_core-0.15.0.dist-info/RECORD
